chkpkg/__init__.py
chkpkg/_cleaner.py
chkpkg/_constants.py
chkpkg/_exceptions.py
chkpkg/_package.py
chkpkg/_require_pytyped.py
chkpkg/_venvs.py
chkpkg/py.typed
chkpkg-0.5.2.dist-info/LICENSE
chkpkg-0.5.2.dist-info/METADATA
chkpkg-0.5.2.dist-info/WHEEL
chkpkg-0.5.2.dist-info/top_level.txt
chkpkg-0.5.2.dist-info/RECORD
