Metadata-Version: 2.1
Name: chkpkg
Version: 0.5.2
Summary: Tests Python package sources to see if they build successfully to a PyPi compatible distribution
Home-page: https://github.com/rtmigo/chkpkg_py#readme
Author: Arteom iG
Author-email: ortemeo@gmail.com
License: MIT
Keywords: package,packaging,distribution,wheel,whl,testing,setup,build,setuptools,twine,pypi,qa,ci
Classifier: License :: OSI Approved :: MIT License
Classifier: Programming Language :: Python :: 3.6
Classifier: Programming Language :: Python :: 3.7
Classifier: Programming Language :: Python :: 3.8
Classifier: Programming Language :: Python :: 3.9
Classifier: Programming Language :: Python :: 3.10
Classifier: Topic :: Software Development :: Build Tools
Classifier: Topic :: Software Development :: Quality Assurance
Classifier: Topic :: Software Development :: Testing
Classifier: Operating System :: POSIX
Classifier: Operating System :: Microsoft :: Windows
Requires-Python: >=3.6
License-File: LICENSE
